<?xml version="1.0" standalone="no"?>

<kickstart>

  <description>
  The R Project for Statistical Computing
  http://www.r-project.org/
  </description>

  <copyright>
  Copyright (c) 2000 - 2008 The Regents of the University of California.
  All rights reserved. Rocks(r) v5.1 www.rocksclusters.org
  </copyright>

  <changelog>
  $Log$
  Revision 1.1  2009/04/20 19:40:53  jhayes
  Added R as an example for roll building.

  </changelog>

  <!-- Set of RPMs to install, surrounded by individual package tags. -->
  <package>xdg-utils</package>
  <package>libRmath</package>
  <package>R</package>

  <!-- Post-installation configuration--typically sh code.  R requires no
       configuration, so this post section is empty. -->
  <post>
  </post>

</kickstart>
